chpy/__init__.py
chpy/build.py
chpy/networks.py
chpy/search.py
chpy/utils.py
chpy-0.1.1.dist-info/METADATA
chpy-0.1.1.dist-info/WHEEL
chpy-0.1.1.dist-info/top_level.txt
chpy-0.1.1.dist-info/RECORD
