Metadata-Version: 2.1
Name: chpy
Version: 0.1.1
Summary: Build networks from the Companies House API
Home-page: https://github.com/specialprocedures/chpy
Author: Ian Goodrich
License: MIT
Platform: UNKNOWN
Classifier: License :: OSI Approved :: MIT License
Classifier: Programming Language :: Python :: 3
Classifier: Programming Language :: Python :: 3.7
